oaiv/__init__.py
oaiv/constants.py
oaiv/core/__init__.py
oaiv/core/account.py
oaiv/modules/__init__.py
oaiv/modules/swap.py
oaiv/tools/__init__.py
oaiv/tools/address.py
oaiv/tools/utils.py
oaiv-0.12.1.dist-info/METADATA
oaiv-0.12.1.dist-info/WHEEL
oaiv-0.12.1.dist-info/top_level.txt
oaiv-0.12.1.dist-info/RECORD
